youqu_mousekey/__init__.py
youqu_mousekey/__version__.py
youqu_mousekey/mousekey.py
youqu_mousekey-2024.6.20.dist-info/METADATA
youqu_mousekey-2024.6.20.dist-info/WHEEL
youqu_mousekey-2024.6.20.dist-info/licenses/LICENSE
youqu_mousekey-2024.6.20.dist-info/RECORD
