Metadata-Version: 2.1
Name: youqu-mousekey
Version: 2024.6.20
Author-email: mikigo <huangmingqiang@uniontech.com>
License: GPL2.0
License-File: LICENSE
Requires-Python: >=3.7
Requires-Dist: funnylog
Requires-Dist: pyautogui==0.9.53
Requires-Dist: pyscreeze==0.1.28
